{
    "os": "Linux-6.5.0-41-generic-x86_64-with-glibc2.35",
    "python": "CPython 3.11.9",
    "heartbeatAt": "2025-04-27T05:53:24.656175",
    "startedAt": "2025-04-27T05:53:24.241354",
    "docker": null,
    "args": [
        "service",
        "--debug",
        "--port-filename",
        "/tmp/tmpnvidxihs/port-3801886.txt",
        "--pid",
        "3801886"
    ],
    "state": "running",
    "program": "/home/alunos/Dados/andre/cooperative-sheaves/neural-sheaf-diffusion/cooperative_sheaves/exp/run.py",
    "codePathLocal": "exp/run.py",
    "codePath": "cooperative_sheaves/exp/run.py",
    "git": {
        "remote": "https://github.com/ML-FGV/neural-sheaf-diffusion.git",
        "commit": "d9e512df9b011f53410726f2925f45dcf2d31b3d"
    },
    "email": "andrerg02@gmail.com",
    "root": "/home/alunos/Dados/andre/cooperative-sheaves/neural-sheaf-diffusion",
    "host": "erj1757",
    "username": null,
    "executable": "/home/alunos/Dados/.pyenv/versions/hsnn/bin/python",
    "cpu_count": 16,
    "cpu_count_logical": 24,
    "cpu_freq": {
        "current": 2975.458875,
        "min": 800.0,
        "max": 4716.666666666667
    },
    "cpu_freq_per_core": [
        {
            "current": 3297.636,
            "min": 800.0,
            "max": 5100.0
        },
        {
            "current": 1994.079,
            "min": 800.0,
            "max": 5100.0
        },
        {
            "current": 3114.153,
            "min": 800.0,
            "max": 5100.0
        },
        {
            "current": 3400.132,
            "min": 800.0,
            "max": 5100.0
        },
        {
            "current": 3031.466,
            "min": 800.0,
            "max": 5100.0
        },
        {
            "current": 3285.537,
            "min": 800.0,
            "max": 5100.0
        },
        {
            "current": 3888.913,
            "min": 800.0,
            "max": 5100.0
        },
        {
            "current": 3746.416,
            "min": 800.0,
            "max": 5100.0
        },
        {
            "current": 3899.982,
            "min": 800.0,
            "max": 5200.0
        },
        {
            "current": 3900.0,
            "min": 800.0,
            "max": 5200.0
        },
        {
            "current": 3848.93,
            "min": 800.0,
            "max": 5100.0
        },
        {
            "current": 3889.6,
            "min": 800.0,
            "max": 5100.0
        },
        {
            "current": 4000.0,
            "min": 800.0,
            "max": 5200.0
        },
        {
            "current": 4000.0,
            "min": 800.0,
            "max": 5200.0
        },
        {
            "current": 3900.0,
            "min": 800.0,
            "max": 5100.0
        },
        {
            "current": 3900.0,
            "min": 800.0,
            "max": 5100.0
        },
        {
            "current": 3885.905,
            "min": 800.0,
            "max": 3900.0
        },
        {
            "current": 3891.915,
            "min": 800.0,
            "max": 3900.0
        },
        {
            "current": 3889.734,
            "min": 800.0,
            "max": 3900.0
        },
        {
            "current": 3891.401,
            "min": 800.0,
            "max": 3900.0
        },
        {
            "current": 799.052,
            "min": 800.0,
            "max": 3900.0
        },
        {
            "current": 1884.282,
            "min": 800.0,
            "max": 3900.0
        },
        {
            "current": 798.987,
            "min": 800.0,
            "max": 3900.0
        },
        {
            "current": 799.414,
            "min": 800.0,
            "max": 3900.0
        }
    ],
    "disk": {
        "/": {
            "total": 469077516288,
            "used": 423060336640
        }
    },
    "gpu": "NVIDIA GeForce RTX 3090",
    "gpu_count": 1,
    "gpu_devices": [
        {
            "name": "NVIDIA GeForce RTX 3090",
            "memory_total": 25769803776
        }
    ],
    "memory": {
        "total": 134735994880
    }
}
